solveur/__init__.py
solveur/solveur.py
solveur-0.1.2.dist-info/METADATA
solveur-0.1.2.dist-info/WHEEL
solveur-0.1.2.dist-info/top_level.txt
solveur-0.1.2.dist-info/RECORD
