Metadata-Version: 2.1
Name: solveur
Version: 0.1.2
Summary: Solveur d'équations de second degré
Home-page: https://github.com/bouquet-cedric/module-python
Author: Bouquet Cédric
Author-email: cedric-bouquet-7@outlook.fr
Classifier: Programming Language :: Python :: 3
Requires-Python: >=3.0
